{
  "intro": {
    "title": "Past Simple and Past Continuous",
    "sections": [
      {
        "title": "Two past tenses, two jobs",
        "content": "**Past simple** = a **completed** action at a specific past time. **Past continuous** = an action **in progress** at a past moment.",
        "diagrams": [
          {
            "type": "timeline",
            "title": "Past simple vs past continuous",
            "events": [
              {
                "label": "action in progress",
                "detail": "past continuous",
                "style": "past"
              },
              {
                "label": "completed action at a specific time",
                "detail": "past simple",
                "style": "past"
              },
              {
                "label": "NOW",
                "style": "now"
              }
            ]
          },
          {
            "type": "formula",
            "items": [
              {
                "label": "Past simple",
                "formula": "did / went / saw → I went, she did"
              },
              {
                "label": "Past continuous",
                "formula": "was/were + -ing → I was going, she was doing"
              }
            ]
          }
        ],
        "root_ids": [
          "A2.past_tense.continuous"
        ],
        "cefr_level": "A2"
      },
      {
        "title": "Past simple: when to use",
        "content": "Use **past simple** for completed events: finished action, specific time, sequence, or a short action interrupting a longer one.",
        "diagrams": [
          {
            "type": "examples",
            "items": [
              {
                "good": "I finished the report. She left at five.",
                "why": "completed action"
              },
              {
                "good": "I saw him yesterday.",
                "why": "specific time"
              },
              {
                "good": "I got up, had breakfast, and went to work.",
                "why": "sequence of events"
              },
              {
                "good": "The phone rang while I was cooking.",
                "why": "short action that interrupts a longer one"
              }
            ]
          },
          {
            "type": "chips",
            "title": "Specific-time signals",
            "items": [
              "yesterday",
              "last week",
              "at 3 o'clock"
            ]
          }
        ],
        "root_ids": [
          "A1.past_tense.simple"
        ],
        "cefr_level": "A1"
      },
      {
        "title": "Past simple: form",
        "content": "**Form:** regular verbs + *-ed*; irregular verbs have their own forms.",
        "diagrams": [
          {
            "type": "formula",
            "items": [
              {
                "label": "regular",
                "formula": "verb + -ed → finished, walked"
              },
              {
                "label": "irregular",
                "formula": "went, saw, wrote"
              }
            ]
          }
        ],
        "root_ids": [
          "A1.past_tense.simple"
        ],
        "cefr_level": "A1"
      },
      {
        "title": "Past continuous: when to use",
        "content": "Use **past continuous** for actions in progress: at a past moment, as background, in parallel, or as a temporary situation.\nForm: **was/were** + verb + *-ing*.",
        "diagrams": [
          {
            "type": "examples",
            "items": [
              {
                "good": "At 8 pm I was watching TV.",
                "why": "action in progress at a past moment"
              },
              {
                "good": "I was walking home when I met a friend.",
                "why": "background / longer action when something else happened"
              },
              {
                "good": "She was cooking while he was setting the table.",
                "why": "two parallel actions"
              },
              {
                "good": "Last year she was working in London.",
                "why": "temporary situation"
              }
            ]
          }
        ],
        "root_ids": [
          "A2.past_tense.continuous"
        ],
        "cefr_level": "A2"
      },
      {
        "title": "Interrupted actions: when and while",
        "content": "When one action **interrupts** another: the **longer** action (in progress) → past continuous; the **shorter** interrupting action → past simple.",
        "diagrams": [
          {
            "type": "formula",
            "items": [
              {
                "label": "pattern",
                "formula": "past continuous (longer) + when + past simple (shorter) → I was reading when the phone rang."
              }
            ]
          },
          {
            "type": "examples",
            "items": [
              {
                "good": "While she was working, the phone rang.",
                "why": "*while* + the longer action in progress"
              },
              {
                "good": "While I was cooking, she was setting the table.",
                "why": "both actions in progress"
              },
              {
                "good": "When I arrived, they were having dinner.",
                "why": "*when* can be followed by either tense"
              }
            ]
          }
        ],
        "root_ids": [
          "A2.past_tense.continuous"
        ],
        "cefr_level": "A2"
      },
      {
        "title": "Side by side",
        "content": "The whole contrast on one card.",
        "diagrams": [
          {
            "type": "comparison",
            "title": "Past simple vs past continuous",
            "left": {
              "title": "Past Simple",
              "points": [
                "Completed action",
                "Specific past time",
                "Sequence of events",
                "Short / interrupting action",
                "Form: did / went / saw"
              ]
            },
            "right": {
              "title": "Past Continuous",
              "points": [
                "Action in progress",
                "Background action",
                "Two parallel actions",
                "Longer action (interrupted)",
                "Form: was/were + -ing"
              ]
            }
          }
        ],
        "root_ids": [
          "A2.past_tense.continuous"
        ],
        "cefr_level": "A2"
      },
      {
        "title": "Which tense?",
        "content": "One question decides it.",
        "diagrams": [
          {
            "type": "decision",
            "title": "Past simple or past continuous?",
            "steps": [
              {
                "q": "In progress at that past moment?",
                "yes": "past continuous (was/were + -ing)"
              },
              {
                "end": "Completed event → past simple"
              }
            ]
          }
        ],
        "root_ids": [
          "A2.past_tense.continuous"
        ],
        "cefr_level": "A2"
      },
      {
        "title": "Typical errors",
        "content": "The trap is always the same: completed event vs action in progress.\nMore past tenses: see the Past Perfect and Past Simple vs Present Perfect topics under Choose Grammar Topic.",
        "diagrams": [
          {
            "type": "examples",
            "items": [
              {
                "good": "I was reading when the phone rang.",
                "bad": "I read when the phone rang.",
                "why": "you were in the middle of reading"
              },
              {
                "good": "The phone rang when I was reading.",
                "bad": "The phone was ringing when I was reading.",
                "why": "it rang once — a single interrupting event"
              },
              {
                "good": "I went to the cinema yesterday.",
                "bad": "I was going to the cinema yesterday.",
                "why": "completed trip"
              },
              {
                "good": "I was reading when she called.",
                "bad": "I read when she called.",
                "why": "otherwise unclear — were you mid-reading?"
              }
            ]
          }
        ],
        "root_ids": [
          "A2.past_tense.continuous"
        ],
        "cefr_level": "A2"
      }
    ]
  },
  "check": {
    "title": "Test your understanding",
    "questions": [
      {
        "type": "mc",
        "question": "'I _____ TV when the phone rang.' (You were in the middle of watching.) Which fits?",
        "options": {
          "a": "was watching",
          "b": "watched",
          "c": "have watched",
          "d": "am watching"
        },
        "correct_option": "a",
        "explanation": "Action in progress when something else happened → past continuous."
      },
      {
        "type": "mc",
        "question": "'She _____ to London yesterday.' (Completed trip.) Which fits?",
        "options": {
          "a": "was going",
          "b": "has gone",
          "c": "went",
          "d": "were going"
        },
        "correct_option": "c",
        "explanation": "Completed action, specific time (yesterday) → past simple."
      },
      {
        "type": "mc",
        "question": "'While he _____ dinner, I was reading.' Which fits?",
        "options": {
          "a": "cooked",
          "b": "cooks",
          "c": "has cooked",
          "d": "was cooking"
        },
        "correct_option": "d",
        "explanation": "Two actions in progress at the same time → past continuous for both."
      },
      {
        "type": "mc",
        "question": "'The doorbell _____ while I was having a shower.' Which fits?",
        "options": {
          "a": "rang",
          "b": "was ringing",
          "c": "rings",
          "d": "has rung"
        },
        "correct_option": "a",
        "explanation": "Short interrupting event → past simple."
      },
      {
        "type": "mc",
        "question": "'At 7 pm last night they _____ .' (They were in the middle of eating.) Which fits?",
        "options": {
          "a": "had dinner",
          "b": "have dinner",
          "c": "were having dinner",
          "d": "had had dinner"
        },
        "correct_option": "c",
        "explanation": "Action in progress at a specific moment → past continuous."
      }
    ],
    "root_ids": [
      "A2.past_tense.continuous"
    ],
    "cefr_level": "A2"
  },
  "practice_order": [
    "gapfill",
    "errorcorrection",
    "mc"
  ],
  "practice": {
    "gapfill": {
      "title": "Practice: Past simple or past continuous?",
      "questions": [
        {
          "type": "open",
          "question": "I _____ (watch) TV when the phone rang.",
          "answers": [
            "was watching"
          ],
          "explanation": "Action in progress when something happened → past continuous."
        },
        {
          "type": "open",
          "question": "I was watching TV when the phone _____ (ring).",
          "answers": [
            "rang"
          ],
          "explanation": "Short interrupting event → past simple."
        },
        {
          "type": "open",
          "question": "She _____ (go) to the cinema yesterday.",
          "answers": [
            "went"
          ],
          "explanation": "Completed action, yesterday → past simple."
        },
        {
          "type": "open",
          "question": "While he _____ (cook), she was setting the table.",
          "answers": [
            "was cooking"
          ],
          "explanation": "Two actions in progress at the same time → past continuous."
        },
        {
          "type": "open",
          "question": "We _____ (have) dinner at 8 pm last night.",
          "answers": [
            "were having"
          ],
          "explanation": "Action in progress at a moment (at 8 pm) → past continuous."
        },
        {
          "type": "open",
          "question": "He _____ (walk) home when he met an old friend.",
          "answers": [
            "was walking"
          ],
          "explanation": "Background action in progress → past continuous."
        },
        {
          "type": "open",
          "question": "They _____ (not watch) the film when I arrived.",
          "answers": [
            "weren't watching",
            "were not watching"
          ],
          "explanation": "Action in progress (negative) when I arrived → past continuous."
        },
        {
          "type": "open",
          "question": "What _____ you _____ (do) when the lights went out?",
          "answers": [
            "were you doing"
          ],
          "explanation": "What were you in the middle of → past continuous."
        },
        {
          "type": "open",
          "question": "I saw him while I _____ (wait) for the bus.",
          "answers": [
            "was waiting"
          ],
          "explanation": "Action in progress (background) → past continuous."
        },
        {
          "type": "open",
          "question": "The phone _____ (ring) while I was having a shower.",
          "answers": [
            "rang"
          ],
          "explanation": "Short interrupting event → past simple."
        },
        {
          "type": "open",
          "question": "She _____ (work) in Paris last year.",
          "answers": [
            "was working",
            "worked"
          ],
          "explanation": "Temporary situation or completed → was working or worked."
        }
      ],
      "root_ids": [
        "A2.past_tense.continuous"
      ],
      "cefr_level": "A2"
    },
    "errorcorrection": {
      "title": "Practice: Correct the tense",
      "questions": [
        {
          "type": "open",
          "question": "Wrong: 'I read when the phone rang.' (You mean you were in the middle of reading.) Correct the sentence.",
          "answers": [
            "I was reading when the phone rang.",
            "I was reading when the phone rang"
          ],
          "explanation": "Action in progress → past continuous (was reading)."
        },
        {
          "type": "open",
          "question": "Wrong: 'She was going to London yesterday.' (She went; the trip is completed.) Correct the sentence.",
          "answers": [
            "She went to London yesterday.",
            "She went to London yesterday"
          ],
          "explanation": "Completed action with yesterday → past simple."
        },
        {
          "type": "open",
          "question": "Wrong: 'The phone was ringing when I was reading.' (The phone rang once and interrupted you.) Correct the sentence.",
          "answers": [
            "The phone rang when I was reading.",
            "The phone rang when I was reading"
          ],
          "explanation": "Short interrupting event → past simple (rang)."
        },
        {
          "type": "open",
          "question": "Wrong: 'While he cooked, she set the table.' (Both were in progress at the same time.) Correct using past continuous where appropriate.",
          "answers": [
            "While he was cooking, she was setting the table.",
            "While he was cooking, she was setting the table"
          ],
          "explanation": "Two parallel actions in progress → past continuous for both."
        },
        {
          "type": "open",
          "question": "Wrong: 'I was seeing him yesterday.' (You met him once; completed.) Correct the sentence.",
          "answers": [
            "I saw him yesterday.",
            "I saw him yesterday"
          ],
          "explanation": "Completed event, yesterday → past simple (saw)."
        },
        {
          "type": "open",
          "question": "Wrong: 'We had dinner at 8 pm.' (You mean you were in the middle of dinner at that moment.) Correct the sentence.",
          "answers": [
            "We were having dinner at 8 pm.",
            "We were having dinner at 8 pm",
            "We were having dinner at 8pm.",
            "We were having dinner at 8pm"
          ],
          "explanation": "Action in progress at a moment → past continuous."
        }
      ],
      "root_ids": [
        "A2.past_tense.continuous"
      ],
      "cefr_level": "A2"
    },
    "mc": {
      "title": "Practice: Past Simple and Past Continuous (multiple choice)",
      "questions": [],
      "root_ids": [
        "A2.past_tense.continuous"
      ],
      "cefr_level": "A2"
    }
  }
}
